epydemicarchive/api/v1/client/__init__.py
epydemicarchive/api/v1/client/client.py
epydemicarchive_client-0.2.1.dist-info/METADATA
epydemicarchive_client-0.2.1.dist-info/WHEEL
epydemicarchive_client-0.2.1.dist-info/top_level.txt
epydemicarchive_client-0.2.1.dist-info/RECORD
