Metadata-Version: 2.1
Name: epydemicarchive-client
Version: 0.2.1
Summary: Client for the epydemic archive
Home-page: http://github.com/simoninireland/epydemicarchive
Author: Simon Dobson
Author-email: simoninireland@gmail.com
License: License :: OSI Approved :: GNU General Public License v3 or later
Platform: UNKNOWN
Classifier: Development Status :: 4 - Beta
Classifier: Intended Audience :: Science/Research
Classifier: Intended Audience :: Developers
Classifier: Programming Language :: Python :: 3.6
Classifier: Programming Language :: Python :: 3.7
Classifier: Programming Language :: Python :: 3.8
Classifier: Programming Language :: Python :: 3.9
Classifier: Topic :: Scientific/Engineering
Requires-Python: >=3.6
Requires-Dist: networkx (>=2.4)
Requires-Dist: requests
Requires-Dist: requests-toolbelt
